[{"admitid": 574274, "institution": "UCLA", "programme": "Computer Science", "level": "PhD", "how": "Phone", "decision": "Other", "date_of_notification": "2018-03-05", "date_of_record": "2018-03-05 21:30:10", "notes": "I called the graduate office and they said that this year they are doing rolling admissions. Apparently, some of the acceptances could go out as late as early April", "status": "A", "ip": "67.171.67.86", "uid": -1, "season": "F18", "ugpa": "0.00", "greq": 0, "grev": 0, "grew": "0.00", "gres": 0, "flag": 0, "user_id": 0, "deactivated_at": null, "formatted_notification_date": "5 Mar", "formatted_record_date": "March 2018", "formatted_season": "Fall 2018", "formatted_added_date": "March 05, 2018"}, {"admitid": 525508, "institution": "UCLA", "programme": "Computer Science", "level": "PhD", "how": "E-mail", "decision": "Rejected", "date_of_notification": "2017-04-10", "date_of_record": "2017-04-12 05:22:12", "notes": "525 applicants for 26 seats.. Mailed the Comp. Science graduate admissions to find out the results.", "status": "U", "ip": "14.139.204.210", "uid": -1, "season": "F17", "ugpa": "3.90", "greq": 166, "grev": 162, "grew": "5.00", "gres": 0, "flag": 0, "user_id": 0, "deactivated_at": null, "formatted_notification_date": "10 Apr", "formatted_record_date": "April 2017", "formatted_season": null, "formatted_added_date": "April 12, 2017"}, {"admitid": 460582, "institution": "UCLA", "programme": "Computer Science", "level": "PhD", "how": "E-mail", "decision": "Rejected", "date_of_notification": "2016-04-13", "date_of_record": "2016-04-13 11:57:33", "notes": "", "status": "U", "ip": "128.205.226.78", "uid": -1, "season": "F16", "ugpa": "0.00", "greq": 0, "grev": 0, "grew": "0.00", "gres": 0, "flag": 0, "user_id": 0, "deactivated_at": null, "formatted_notification_date": "13 Apr", "formatted_record_date": "April 2016", "formatted_season": null, "formatted_added_date": "April 13, 2016"}, {"admitid": 460105, "institution": "UCLA", "programme": "Computer Science", "level": "PhD", "how": "Website", "decision": "Rejected", "date_of_notification": "2016-04-12", "date_of_record": "2016-04-12 11:09:37", "notes": "Received an email to check status. Website shows the decision:\r\nThank you for applying to graduate study at UCLA. We regret to inform you that you are not being offered admission.\r\nUCLA receives many more applications than there are student places available. Each of these applications is carefully reviewed by a departmental faculty committee. In this extremely competitive environment, many talented and promising students are not recommended for admission by these committees.", "status": "I", "ip": "1.162.89.23", "uid": -1, "season": "F16", "ugpa": "0.00", "greq": 0, "grev": 0, "grew": "0.00", "gres": 0, "flag": 0, "user_id": 0, "deactivated_at": null, "formatted_notification_date": "12 Apr", "formatted_record_date": "April 2016", "formatted_season": null, "formatted_added_date": "April 12, 2016"}, {"admitid": 459674, "institution": "UCLA", "programme": "Computer Science", "level": "PhD", "how": "E-mail", "decision": "Wait listed", "date_of_notification": "2016-04-08", "date_of_record": "2016-04-11 07:24:48", "notes": "UCLA is my #1 choice! If any other theory applicants know they won't be attending, it would mean the world to me if you'd decline soon!", "status": "A", "ip": "166.170.14.50", "uid": -1, "season": "F16", "ugpa": "0.00", "greq": 0, "grev": 0, "grew": "0.00", "gres": 0, "flag": 0, "user_id": 0, "deactivated_at": null, "formatted_notification_date": "8 Apr", "formatted_record_date": "April 2016", "formatted_season": null, "formatted_added_date": "April 11, 2016"}, {"admitid": 454528, "institution": "UCLA", "programme": "Computer Science", "level": "PhD", "how": "Website", "decision": "Rejected", "date_of_notification": "2016-03-29", "date_of_record": "2016-03-30 03:51:35", "notes": "Didn't contact any professor before, and be rejected without doubt .", "status": "I", "ip": "111.200.13.249", "uid": -1, "season": "F16", "ugpa": "3.60", "greq": 164, "grev": 159, "grew": "3.00", "gres": 0, "flag": 0, "user_id": 0, "deactivated_at": null, "formatted_notification_date": "29 Mar", "formatted_record_date": "March 2016", "formatted_season": null, "formatted_added_date": "March 30, 2016"}, {"admitid": 450476, "institution": "UCLA", "programme": "Computer Science", "level": "PhD", "how": "E-mail", "decision": "Wait listed", "date_of_notification": "2016-03-22", "date_of_record": "2016-03-22 15:09:16", "notes": "To the post asking for the area: AI.", "status": "O", "ip": "71.60.19.118", "uid": -1, "season": "F16", "ugpa": "0.00", "greq": 0, "grev": 0, "grew": "0.00", "gres": 0, "flag": 0, "user_id": 0, "deactivated_at": null, "formatted_notification_date": "22 Mar", "formatted_record_date": "March 2016", "formatted_season": null, "formatted_added_date": "March 22, 2016"}, {"admitid": 443036, "institution": "UCLA (University Of California Los Angeles)", "programme": "Computer Science", "level": "PhD", "how": "E-mail", "decision": "Rejected", "date_of_notification": "2016-03-11", "date_of_record": "2016-03-11 20:27:20", "notes": "", "status": "", "ip": "130.14.254.24", "uid": -1, "season": "F16", "ugpa": "0.00", "greq": 0, "grev": 0, "grew": "0.00", "gres": 0, "flag": 0, "user_id": 0, "deactivated_at": null, "formatted_notification_date": "11 Mar", "formatted_record_date": "March 2016", "formatted_season": null, "formatted_added_date": "March 11, 2016"}, {"admitid": 438107, "institution": "UCLA", "programme": "Computer Science", "level": "PhD", "how": "Other", "decision": "Other", "date_of_notification": "2016-03-07", "date_of_record": "2016-03-07 19:11:56", "notes": "To all UCLA applicants below, I am one of the admitted UCLA CS PhD students, and I have already attended UCLA's open house for CS PhD last Thursday, so if you haven't heard anything back yet, you can assume you're either waitlisted or rejected.", "status": "U", "ip": "128.46.76.7", "uid": -1, "season": "F16", "ugpa": "0.00", "greq": 0, "grev": 0, "grew": "0.00", "gres": 0, "flag": 0, "user_id": 0, "deactivated_at": null, "formatted_notification_date": "7 Mar", "formatted_record_date": "March 2016", "formatted_season": null, "formatted_added_date": "March 07, 2016"}, {"admitid": 435456, "institution": "UCLA", "programme": "Computer Science", "level": "PhD", "how": "Other", "decision": "Other", "date_of_notification": "2016-03-04", "date_of_record": "2016-03-04 14:42:00", "notes": "Does anyone know about Computer Science PhD results? It seems the department is mostly gave Masters admissions, right?", "status": "I", "ip": "132.205.236.66", "uid": -1, "season": "F16", "ugpa": "0.00", "greq": 0, "grev": 0, "grew": "0.00", "gres": 0, "flag": 0, "user_id": 0, "deactivated_at": null, "formatted_notification_date": "4 Mar", "formatted_record_date": "March 2016", "formatted_season": null, "formatted_added_date": "March 04, 2016"}, {"admitid": 409464, "institution": "UCLA", "programme": "Computer Science", "level": "PhD", "how": "E-mail", "decision": "Accepted", "date_of_notification": "2016-02-04", "date_of_record": "2016-02-04 23:31:56", "notes": "Computer Vision!", "status": "I", "ip": "169.232.149.143", "uid": -1, "season": "F16", "ugpa": "0.00", "greq": 0, "grev": 0, "grew": "0.00", "gres": 0, "flag": 0, "user_id": 0, "deactivated_at": null, "formatted_notification_date": "4 Feb", "formatted_record_date": "February 2016", "formatted_season": null, "formatted_added_date": "February 04, 2016"}, {"admitid": 406326, "institution": "UCLA (University Of California, Los Angeles)", "programme": "Computer Science", "level": "PhD", "how": "E-mail", "decision": "Interview", "date_of_notification": "2016-01-30", "date_of_record": "2016-01-31 06:46:47", "notes": "A professor mentioned in my SOP asked for an interview", "status": "I", "ip": "41.196.253.246", "uid": -1, "season": "F16", "ugpa": "3.92", "greq": 166, "grev": 149, "grew": "4.00", "gres": 0, "flag": 0, "user_id": 0, "deactivated_at": null, "formatted_notification_date": "30 Jan", "formatted_record_date": "January 2016", "formatted_season": null, "formatted_added_date": "January 31, 2016"}, {"admitid": 400983, "institution": "UCLA", "programme": "Computer Science", "level": "PhD", "how": "E-mail", "decision": "Interview", "date_of_notification": "2015-12-27", "date_of_record": "2016-01-16 13:53:09", "notes": "Professor I mentioned in the SOP emailed for an interview.", "status": "I", "ip": "198.84.188.76", "uid": -1, "season": "F16", "ugpa": "0.00", "greq": 0, "grev": 0, "grew": "0.00", "gres": 0, "flag": 0, "user_id": 0, "deactivated_at": null, "formatted_notification_date": "27 Dec", "formatted_record_date": "January 2016", "formatted_season": null, "formatted_added_date": "January 16, 2016"}, {"admitid": 389251, "institution": "UCLA", "programme": "Computer Science", "level": "PhD", "how": "E-mail", "decision": "Rejected", "date_of_notification": "2015-04-10", "date_of_record": "2015-04-10 14:42:47", "notes": "", "status": "U", "ip": "76.167.140.237", "uid": -1, "season": "F15", "ugpa": "0.00", "greq": 0, "grev": 0, "grew": "0.00", "gres": 0, "flag": 0, "user_id": 0, "deactivated_at": null, "formatted_notification_date": "10 Apr", "formatted_record_date": "April 2015", "formatted_season": null, "formatted_added_date": "April 10, 2015"}, {"admitid": 389216, "institution": "UCLA", "programme": "Computer Science", "level": "PhD", "how": "E-mail", "decision": "Rejected", "date_of_notification": "2015-04-10", "date_of_record": "2015-04-10 11:47:04", "notes": "my dream university :((((((((((", "status": "I", "ip": "31.59.17.82", "uid": -1, "season": "F15", "ugpa": "3.68", "greq": 170, "grev": 141, "grew": "3.50", "gres": 0, "flag": 0, "user_id": 0, "deactivated_at": null, "formatted_notification_date": "10 Apr", "formatted_record_date": "April 2015", "formatted_season": null, "formatted_added_date": "April 10, 2015"}, {"admitid": 388800, "institution": "UCLA", "programme": "Computer Science", "level": "PhD", "how": "E-mail", "decision": "Rejected", "date_of_notification": "2015-04-09", "date_of_record": "2015-04-09 14:52:33", "notes": "Emailed to check website. Focus in AI.", "status": "A", "ip": "68.0.214.29", "uid": 206336, "season": "F15", "ugpa": "3.80", "greq": 168, "grev": 160, "grew": "4.50", "gres": 0, "flag": 0, "user_id": 0, "deactivated_at": null, "formatted_notification_date": "9 Apr", "formatted_record_date": "April 2015", "formatted_season": null, "formatted_added_date": "April 09, 2015"}, {"admitid": 388762, "institution": "UCLA", "programme": "Computer Science", "level": "PhD", "how": "E-mail", "decision": "Wait listed", "date_of_notification": "2015-04-09", "date_of_record": "2015-04-09 13:20:16", "notes": "Please kindly decline your UCLA offer if you do not plan to go there. Thank you very much! April 15th is coming!!!", "status": "I", "ip": "143.89.94.52", "uid": 201639, "season": "F15", "ugpa": "0.00", "greq": 0, "grev": 0, "grew": "0.00", "gres": 0, "flag": 0, "user_id": 0, "deactivated_at": null, "formatted_notification_date": "9 Apr", "formatted_record_date": "April 2015", "formatted_season": null, "formatted_added_date": "April 09, 2015"}, {"admitid": 388054, "institution": "UCLA", "programme": "Computer Science", "level": "PhD", "how": "E-mail", "decision": "Wait listed", "date_of_notification": "2015-04-08", "date_of_record": "2015-04-08 04:36:17", "notes": "If you have an offer from UCLA and don't plan on accepting PLEASE REJECT :)", "status": "O", "ip": "68.0.214.29", "uid": 206336, "season": "F15", "ugpa": "0.00", "greq": 0, "grev": 0, "grew": "0.00", "gres": 0, "flag": 0, "user_id": 0, "deactivated_at": null, "formatted_notification_date": "8 Apr", "formatted_record_date": "April 2015", "formatted_season": null, "formatted_added_date": "April 08, 2015"}, {"admitid": 387363, "institution": "UCLA", "programme": "Computer Science", "level": "PhD", "how": "Phone", "decision": "Accepted", "date_of_notification": "2015-04-06", "date_of_record": "2015-04-06 20:31:34", "notes": "", "status": "I", "ip": "66.171.229.182", "uid": -1, "season": "F15", "ugpa": "3.82", "greq": 163, "grev": 149, "grew": "3.00", "gres": 0, "flag": 0, "user_id": 0, "deactivated_at": null, "formatted_notification_date": "6 Apr", "formatted_record_date": "April 2015", "formatted_season": null, "formatted_added_date": "April 06, 2015"}, {"admitid": 386946, "institution": "UCLA", "programme": "Computer Science", "level": "PhD", "how": "E-mail", "decision": "Rejected", "date_of_notification": "2015-04-04", "date_of_record": "2015-04-04 20:39:21", "notes": "", "status": "U", "ip": "50.202.180.242", "uid": -1, "season": "F15", "ugpa": "0.00", "greq": 0, "grev": 0, "grew": "0.00", "gres": 0, "flag": 0, "user_id": 0, "deactivated_at": null, "formatted_notification_date": "4 Apr", "formatted_record_date": "April 2015", "formatted_season": null, "formatted_added_date": "April 04, 2015"}, {"admitid": 386540, "institution": "UCLA", "programme": "Computer Science", "level": "PhD", "how": "Other", "decision": "Wait listed", "date_of_notification": "2015-04-03", "date_of_record": "2015-04-03 16:53:13", "notes": "People accepted but not interested in UCLA or UCI PhD CS please make your decision soon.\r\nThanks.", "status": "O", "ip": "35.2.85.61", "uid": 0, "season": "F15", "ugpa": "0.00", "greq": 0, "grev": 0, "grew": "0.00", "gres": 0, "flag": 0, "user_id": 0, "deactivated_at": null, "formatted_notification_date": "3 Apr", "formatted_record_date": "April 2015", "formatted_season": null, "formatted_added_date": "April 03, 2015"}, {"admitid": 385703, "institution": "UCLA", "programme": "Computer Science", "level": "PhD", "how": "E-mail", "decision": "Wait listed", "date_of_notification": "2015-04-02", "date_of_record": "2015-04-02 03:24:17", "notes": "I found that I am in the same situation as the below UCLA poster. Please decline your UCLA offer if you do not plan to go there. Thank you very much!", "status": "I", "ip": "143.89.68.150", "uid": -1, "season": "F15", "ugpa": "0.00", "greq": 0, "grev": 0, "grew": "0.00", "gres": 0, "flag": 0, "user_id": 0, "deactivated_at": null, "formatted_notification_date": "2 Apr", "formatted_record_date": "April 2015", "formatted_season": null, "formatted_added_date": "April 02, 2015"}, {"admitid": 385067, "institution": "UCLA", "programme": "Computer Science", "level": "PhD", "how": "E-mail", "decision": "Wait listed", "date_of_notification": "2015-04-01", "date_of_record": "2015-04-01 09:06:21", "notes": "Steve replied \"You are among one of top Graphics and Vision applicants, however, admission offers have been sent to the very top tier applicants for whom we have funding. We will contact you before April 15 if funding becomes available due to any declines of our offers.\"\r\n\r\nPlease decline if you do not plan to go there. Many many thanks :)", "status": "I", "ip": "104.194.231.250", "uid": -1, "season": "F15", "ugpa": "0.00", "greq": 0, "grev": 0, "grew": "0.00", "gres": 0, "flag": 0, "user_id": 0, "deactivated_at": null, "formatted_notification_date": "1 Apr", "formatted_record_date": "April 2015", "formatted_season": null, "formatted_added_date": "April 01, 2015"}, {"admitid": 370107, "institution": "UCLA", "programme": "Computer Science", "level": "PhD", "how": "E-mail", "decision": "Other", "date_of_notification": "2015-03-11", "date_of_record": "2015-03-11 11:43:27", "notes": "Got a mail to check https://appstatus.grad.ucla.edu/ for decision.", "status": "O", "ip": "223.228.209.189", "uid": -1, "season": "F15", "ugpa": "0.00", "greq": 0, "grev": 0, "grew": "0.00", "gres": 0, "flag": 0, "user_id": 0, "deactivated_at": null, "formatted_notification_date": "11 Mar", "formatted_record_date": "March 2015", "formatted_season": null, "formatted_added_date": "March 11, 2015"}, {"admitid": 370106, "institution": "UCLA", "programme": "Computer Science", "level": "PhD", "how": "E-mail", "decision": "Other", "date_of_notification": "2015-03-11", "date_of_record": "2015-03-11 11:42:00", "notes": "Got a mail to check https://appstatus.grad.ucla.edu/ for decision.", "status": "O", "ip": "223.228.209.189", "uid": -1, "season": "F15", "ugpa": "0.00", "greq": 0, "grev": 0, "grew": "0.00", "gres": 0, "flag": 0, "user_id": 0, "deactivated_at": null, "formatted_notification_date": "11 Mar", "formatted_record_date": "March 2015", "formatted_season": null, "formatted_added_date": "March 11, 2015"}, {"admitid": 370078, "institution": "UCLA", "programme": "Computer Science", "level": "PhD", "how": "Website", "decision": "Rejected", "date_of_notification": "2015-03-11", "date_of_record": "2015-03-11 10:09:31", "notes": "Expected.", "status": "I", "ip": "14.141.35.115", "uid": -1, "season": "F15", "ugpa": "3.80", "greq": 170, "grev": 154, "grew": "4.50", "gres": 0, "flag": 0, "user_id": 0, "deactivated_at": null, "formatted_notification_date": "11 Mar", "formatted_record_date": "March 2015", "formatted_season": null, "formatted_added_date": "March 11, 2015"}, {"admitid": 368634, "institution": "UCLA", "programme": "Computer Science", "level": "PhD", "how": "E-mail", "decision": "Rejected", "date_of_notification": "2015-03-09", "date_of_record": "2015-03-10 02:41:23", "notes": "Emailed to ask and got a respond. The official notice will be sent out in a couple of days.", "status": "U", "ip": "199.111.190.107", "uid": -1, "season": "F15", "ugpa": "0.00", "greq": 0, "grev": 0, "grew": "0.00", "gres": 0, "flag": 0, "user_id": 0, "deactivated_at": null, "formatted_notification_date": "9 Mar", "formatted_record_date": "March 2015", "formatted_season": null, "formatted_added_date": "March 10, 2015"}, {"admitid": 364117, "institution": "UCLA", "programme": "Computer Science", "level": "PhD", "how": "E-mail", "decision": "Rejected", "date_of_notification": "2015-03-05", "date_of_record": "2015-03-05 06:33:59", "notes": "Mailed the Graduate School asking for status. They replied that i was not accepted.", "status": "I", "ip": "14.141.35.115", "uid": -1, "season": "F15", "ugpa": "3.80", "greq": 170, "grev": 154, "grew": "4.50", "gres": 0, "flag": 0, "user_id": 0, "deactivated_at": null, "formatted_notification_date": "5 Mar", "formatted_record_date": "March 2015", "formatted_season": null, "formatted_added_date": "March 05, 2015"}, {"admitid": 335765, "institution": "UCLA", "programme": "Computer Science", "level": "PhD", "how": "E-mail", "decision": "Interview", "date_of_notification": "2015-01-30", "date_of_record": "2015-01-30 21:50:13", "notes": "With POI", "status": "I", "ip": "111.68.103.164", "uid": -1, "season": "F15", "ugpa": "3.77", "greq": 156, "grev": 160, "grew": "3.00", "gres": 0, "flag": 0, "user_id": 0, "deactivated_at": null, "formatted_notification_date": "30 Jan", "formatted_record_date": "January 2015", "formatted_season": null, "formatted_added_date": "January 30, 2015"}, {"admitid": 333253, "institution": "UCLA", "programme": "Computer Science", "level": "PhD", "how": "E-mail", "decision": "Accepted", "date_of_notification": "2015-01-21", "date_of_record": "2015-01-25 07:43:16", "notes": "", "status": "I", "ip": "122.166.151.89", "uid": -1, "season": "F15", "ugpa": "0.00", "greq": 0, "grev": 0, "grew": "0.00", "gres": 0, "flag": 0, "user_id": 0, "deactivated_at": null, "formatted_notification_date": "21 Jan", "formatted_record_date": "January 2015", "formatted_season": null, "formatted_added_date": "January 25, 2015"}, {"admitid": 331941, "institution": "UCLA", "programme": "Computer Science", "level": "PhD", "how": "E-mail", "decision": "Accepted", "date_of_notification": "2015-01-21", "date_of_record": "2015-01-21 17:02:32", "notes": "", "status": "A", "ip": "140.180.251.221", "uid": -1, "season": "F15", "ugpa": "0.00", "greq": 0, "grev": 0, "grew": "0.00", "gres": 0, "flag": 0, "user_id": 0, "deactivated_at": null, "formatted_notification_date": "21 Jan", "formatted_record_date": "January 2015", "formatted_season": null, "formatted_added_date": "January 21, 2015"}, {"admitid": 323649, "institution": "UCLA", "programme": "Computer Science", "level": "PhD", "how": "Other", "decision": "Other", "date_of_notification": "2014-04-09", "date_of_record": "2014-04-23 17:18:52", "notes": "To the poster below. Indeed I haven't received them either. The date 4/21 was evaluated by Steve, but I guess their graduate division could be just having too many files to make. Hope they will come soon.", "status": "I", "ip": "140.207.196.3", "uid": -1, "season": "F14", "ugpa": "0.00", "greq": 0, "grev": 0, "grew": "0.00", "gres": 0, "flag": 0, "user_id": 0, "deactivated_at": null, "formatted_notification_date": "9 Apr", "formatted_record_date": "April 2014", "formatted_season": null, "formatted_added_date": "April 23, 2014"}, {"admitid": 307131, "institution": "UCLA", "programme": "Computer Science", "level": "PhD", "how": "E-mail", "decision": "Rejected", "date_of_notification": "2014-03-17", "date_of_record": "2014-03-18 10:47:18", "notes": "Feeling sad :(", "status": "I", "ip": "122.177.11.165", "uid": -1, "season": "F14", "ugpa": "0.00", "greq": 0, "grev": 0, "grew": "0.00", "gres": 0, "flag": 0, "user_id": 0, "deactivated_at": null, "formatted_notification_date": "17 Mar", "formatted_record_date": "March 2014", "formatted_season": null, "formatted_added_date": "March 18, 2014"}, {"admitid": 307117, "institution": "UCLA", "programme": "Computer Science", "level": "PhD", "how": "E-mail", "decision": "Rejected", "date_of_notification": "2014-03-18", "date_of_record": "2014-03-18 10:01:13", "notes": "2 journals, 6 conference paper (two of them are first author, not first-tier). POI was interested in me, but I cannot pass TOEFL (81 & 85) before they made final decision.", "status": "I", "ip": "140.109.16.166", "uid": -1, "season": "F14", "ugpa": "3.70", "greq": 163, "grev": 143, "grew": "4.00", "gres": 0, "flag": 0, "user_id": 0, "deactivated_at": null, "formatted_notification_date": "18 Mar", "formatted_record_date": "March 2014", "formatted_season": null, "formatted_added_date": "March 18, 2014"}, {"admitid": 307068, "institution": "UCLA", "programme": "Computer Science", "level": "PhD", "how": "E-mail", "decision": "Rejected", "date_of_notification": "2014-03-18", "date_of_record": "2014-03-18 06:05:48", "notes": "", "status": "U", "ip": "197.132.242.210", "uid": -1, "season": "F14", "ugpa": "0.00", "greq": 0, "grev": 0, "grew": "0.00", "gres": 0, "flag": 0, "user_id": 0, "deactivated_at": null, "formatted_notification_date": "18 Mar", "formatted_record_date": "March 2014", "formatted_season": null, "formatted_added_date": "March 18, 2014"}, {"admitid": 306925, "institution": "UCLA", "programme": "Computer Science", "level": "PhD", "how": "E-mail", "decision": "Rejected", "date_of_notification": "2014-03-18", "date_of_record": "2014-03-18 02:06:17", "notes": "5th reject..", "status": "I", "ip": "122.167.70.77", "uid": 174063, "season": "F14", "ugpa": "0.00", "greq": 0, "grev": 0, "grew": "0.00", "gres": 0, "flag": 0, "user_id": 0, "deactivated_at": null, "formatted_notification_date": "18 Mar", "formatted_record_date": "March 2014", "formatted_season": null, "formatted_added_date": "March 18, 2014"}, {"admitid": 306910, "institution": "UCLA", "programme": "Computer Science", "level": "PhD", "how": "E-mail", "decision": "Rejected", "date_of_notification": "2014-03-18", "date_of_record": "2014-03-18 01:51:00", "notes": "4th rejection....", "status": "I", "ip": "113.200.81.14", "uid": -1, "season": "F14", "ugpa": "0.00", "greq": 0, "grev": 0, "grew": "0.00", "gres": 0, "flag": 0, "user_id": 0, "deactivated_at": null, "formatted_notification_date": "18 Mar", "formatted_record_date": "March 2014", "formatted_season": null, "formatted_added_date": "March 18, 2014"}, {"admitid": 306894, "institution": "UCLA", "programme": "Computer Science", "level": "PhD", "how": "E-mail", "decision": "Rejected", "date_of_notification": "2014-03-18", "date_of_record": "2014-03-18 01:31:48", "notes": "I think their notification is too late...", "status": "I", "ip": "143.89.228.49", "uid": -1, "season": "F14", "ugpa": "0.00", "greq": 0, "grev": 0, "grew": "0.00", "gres": 0, "flag": 0, "user_id": 0, "deactivated_at": null, "formatted_notification_date": "18 Mar", "formatted_record_date": "March 2014", "formatted_season": null, "formatted_added_date": "March 18, 2014"}, {"admitid": 306879, "institution": "UCLA", "programme": "Computer Science", "level": "PhD", "how": "E-mail", "decision": "Rejected", "date_of_notification": "2014-03-18", "date_of_record": "2014-03-18 01:01:38", "notes": "", "status": "I", "ip": "202.120.40.98", "uid": -1, "season": "F14", "ugpa": "0.00", "greq": 0, "grev": 0, "grew": "0.00", "gres": 0, "flag": 0, "user_id": 0, "deactivated_at": null, "formatted_notification_date": "18 Mar", "formatted_record_date": "March 2014", "formatted_season": null, "formatted_added_date": "March 18, 2014"}, {"admitid": 306862, "institution": "UCLA", "programme": "Computer Science", "level": "PhD", "how": "E-mail", "decision": "Rejected", "date_of_notification": "2014-03-18", "date_of_record": "2014-03-18 00:49:22", "notes": "", "status": "I", "ip": "161.122.201.184", "uid": -1, "season": "F14", "ugpa": "3.74", "greq": 155, "grev": 164, "grew": "3.00", "gres": 0, "flag": 0, "user_id": 0, "deactivated_at": null, "formatted_notification_date": "18 Mar", "formatted_record_date": "March 2014", "formatted_season": null, "formatted_added_date": "March 18, 2014"}, {"admitid": 305526, "institution": "UCLA", "programme": "Computer Science", "level": "PhD", "how": "E-mail", "decision": "Rejected", "date_of_notification": "2014-03-15", "date_of_record": "2014-03-15 10:27:51", "notes": "Email to check the website. And the 4th rejection", "status": "I", "ip": "197.195.183.157", "uid": 126398, "season": "F14", "ugpa": "3.42", "greq": 170, "grev": 142, "grew": "3.00", "gres": 0, "flag": 0, "user_id": 0, "deactivated_at": null, "formatted_notification_date": "15 Mar", "formatted_record_date": "March 2014", "formatted_season": null, "formatted_added_date": "March 15, 2014"}, {"admitid": 299474, "institution": "UCLA", "programme": "Computer Science", "level": "PhD", "how": "E-mail", "decision": "Rejected", "date_of_notification": "2014-03-10", "date_of_record": "2014-03-10 16:37:02", "notes": "To the poster below: Do what you LOVE. Go to study with your dream CS professor. Good Luck :)", "status": "I", "ip": "41.34.231.189", "uid": -1, "season": "F14", "ugpa": "0.00", "greq": 0, "grev": 0, "grew": "0.00", "gres": 0, "flag": 0, "user_id": 0, "deactivated_at": null, "formatted_notification_date": "10 Mar", "formatted_record_date": "March 2014", "formatted_season": null, "formatted_added_date": "March 10, 2014"}, {"admitid": 298810, "institution": "UCLA", "programme": "Computer Science", "level": "PhD", "how": "E-mail", "decision": "Accepted", "date_of_notification": "2014-03-04", "date_of_record": "2014-03-09 12:40:39", "notes": "Looking for a little help or which program to choose.  University of California, Irvine, full funding and research.  However, I heard the professor is a stuck up.  University of California, Davis, no funding but research with my dream CS professor.  Currently waitlisted at my former undergraduate school, UCLA.  Could someone tell me what to do?", "status": "A", "ip": "208.72.142.6", "uid": 177592, "season": "F14", "ugpa": "0.00", "greq": 0, "grev": 0, "grew": "0.00", "gres": 0, "flag": 0, "user_id": 0, "deactivated_at": null, "formatted_notification_date": "4 Mar", "formatted_record_date": "March 2014", "formatted_season": null, "formatted_added_date": "March 09, 2014"}, {"admitid": 296828, "institution": "UCLA", "programme": "Computer Science", "level": "PhD", "how": "E-mail", "decision": "Rejected", "date_of_notification": "2014-03-07", "date_of_record": "2014-03-07 07:53:21", "notes": "I asked the admission office and they replied that I am rejected. All admission notices will be sent within 5-6 business days.", "status": "I", "ip": "41.34.192.118", "uid": -1, "season": "F14", "ugpa": "3.70", "greq": 167, "grev": 149, "grew": "3.50", "gres": 0, "flag": 0, "user_id": 0, "deactivated_at": null, "formatted_notification_date": "7 Mar", "formatted_record_date": "March 2014", "formatted_season": null, "formatted_added_date": "March 07, 2014"}, {"admitid": 294024, "institution": "UCLA", "programme": "Computer Science", "level": "PhD", "how": "E-mail", "decision": "Accepted", "date_of_notification": "2014-03-05", "date_of_record": "2014-03-05 06:45:52", "notes": "From Sharif University, EE minor in CE, no pubs, RAship offered", "status": "I", "ip": "81.31.247.10", "uid": -1, "season": "F14", "ugpa": "0.00", "greq": 170, "grev": 151, "grew": "3.50", "gres": 0, "flag": 0, "user_id": 0, "deactivated_at": null, "formatted_notification_date": "5 Mar", "formatted_record_date": "March 2014", "formatted_season": null, "formatted_added_date": "March 05, 2014"}, {"admitid": 286799, "institution": "UCLA", "programme": "Computer Science", "level": "PhD", "how": "E-mail", "decision": "Rejected", "date_of_notification": "2014-02-26", "date_of_record": "2014-02-26 14:33:35", "notes": "", "status": "U", "ip": "66.213.67.10", "uid": -1, "season": "F14", "ugpa": "0.00", "greq": 0, "grev": 0, "grew": "0.00", "gres": 0, "flag": 0, "user_id": 0, "deactivated_at": null, "formatted_notification_date": "26 Feb", "formatted_record_date": "February 2014", "formatted_season": null, "formatted_added_date": "February 26, 2014"}, {"admitid": 283700, "institution": "UCLA", "programme": "Computer Science (CS)", "level": "PhD", "how": "E-mail", "decision": "Interview", "date_of_notification": "2014-02-23", "date_of_record": "2014-02-23 03:33:27", "notes": "", "status": "I", "ip": "36.228.254.107", "uid": -1, "season": "F14", "ugpa": "3.67", "greq": 169, "grev": 141, "grew": "3.00", "gres": 0, "flag": 0, "user_id": 0, "deactivated_at": null, "formatted_notification_date": "23 Feb", "formatted_record_date": "February 2014", "formatted_season": null, "formatted_added_date": "February 23, 2014"}, {"admitid": 278137, "institution": "UCLA", "programme": "Computer Science", "level": "PhD", "how": "Other", "decision": "Rejected", "date_of_notification": "2014-02-18", "date_of_record": "2014-02-18 01:19:22", "notes": "The admissions committee has made admission offers to some applicants so far", "status": "I", "ip": "123.161.60.122", "uid": -1, "season": "F14", "ugpa": "0.00", "greq": 0, "grev": 0, "grew": "0.00", "gres": 0, "flag": 0, "user_id": 0, "deactivated_at": null, "formatted_notification_date": "18 Feb", "formatted_record_date": "February 2014", "formatted_season": null, "formatted_added_date": "February 18, 2014"}, {"admitid": 277825, "institution": "UCLA", "programme": "Computer Science", "level": "PhD", "how": "Other", "decision": "Other", "date_of_notification": "2014-02-17", "date_of_record": "2014-02-17 19:44:16", "notes": "I've sent to UCLA Computer Science Graduate Admission at the facebook page asking about the status and the reply is \"Thank you for your continued interest in UCLA. We hope to email admission announcements to all Ph.D. applicants February 1-28 and to all M.S. applicants March 1-31. Thank you very much for your patience and assistance.\"", "status": "I", "ip": "105.202.37.93", "uid": 126398, "season": "F14", "ugpa": "0.00", "greq": 0, "grev": 0, "grew": "0.00", "gres": 0, "flag": 0, "user_id": 0, "deactivated_at": null, "formatted_notification_date": "17 Feb", "formatted_record_date": "February 2014", "formatted_season": null, "formatted_added_date": "February 17, 2014"}, {"admitid": 277094, "institution": "UCLA", "programme": "Computer Science", "level": "PhD", "how": "E-mail", "decision": "Other", "date_of_notification": "2014-02-15", "date_of_record": "2014-02-15 21:04:40", "notes": "I posted the reject decision from UCLA below. I checked the website link for decision. It shows \"Submitted - Pending Decision\". But my POI replied :  \"I believe the department did email out PhD acceptance decision in early February.\"", "status": "U", "ip": "76.103.107.114", "uid": 0, "season": "F14", "ugpa": "0.00", "greq": 0, "grev": 0, "grew": "0.00", "gres": 0, "flag": 0, "user_id": 0, "deactivated_at": null, "formatted_notification_date": "15 Feb", "formatted_record_date": "February 2014", "formatted_season": null, "formatted_added_date": "February 15, 2014"}, {"admitid": 277072, "institution": "UCLA", "programme": "Computer Science", "level": "PhD", "how": "E-mail", "decision": "Rejected", "date_of_notification": "2014-02-15", "date_of_record": "2014-02-15 19:51:39", "notes": "Sent email to POI. Got reply that all the acceptance decisions are sent out in early Feb.", "status": "U", "ip": "76.103.107.114", "uid": 0, "season": "F14", "ugpa": "0.00", "greq": 0, "grev": 0, "grew": "0.00", "gres": 0, "flag": 0, "user_id": 0, "deactivated_at": null, "formatted_notification_date": "15 Feb", "formatted_record_date": "February 2014", "formatted_season": null, "formatted_added_date": "February 15, 2014"}, {"admitid": 267248, "institution": "UCLA", "programme": "Computer Science", "level": "PhD", "how": "E-mail", "decision": "Accepted", "date_of_notification": "2014-02-03", "date_of_record": "2014-02-03 08:03:08", "notes": "Acceptance notification received a few hours after a Skype discussion with POI. Detailed financial support offer to arrive in the next 2-3 days. 22 years old, GPA 9.2/10-->expected top 3% percent of my class,1.5 year of undergraduate research experience, one journal publication into finalization phase before submission, 2 years of professional experience, descent GRE and TOEFL.", "status": "I", "ip": "147.102.13.2", "uid": -1, "season": "F14", "ugpa": "0.00", "greq": 0, "grev": 0, "grew": "0.00", "gres": 0, "flag": 0, "user_id": 0, "deactivated_at": null, "formatted_notification_date": "3 Feb", "formatted_record_date": "February 2014", "formatted_season": null, "formatted_added_date": "February 03, 2014"}, {"admitid": 266926, "institution": "UCLA", "programme": "Computer Science", "level": "PhD", "how": "E-mail", "decision": "Accepted", "date_of_notification": "2014-02-01", "date_of_record": "2014-02-01 19:03:36", "notes": "Got email from POI saying I \"will almost certainly be admitted\" two days ago, and \"finial decision will be made in a day or two\". Now just got the offer, campus visit days:March 6-7.", "status": "I", "ip": "198.166.38.241", "uid": -1, "season": "F14", "ugpa": "0.00", "greq": 0, "grev": 0, "grew": "0.00", "gres": 0, "flag": 0, "user_id": 0, "deactivated_at": null, "formatted_notification_date": "1 Feb", "formatted_record_date": "February 2014", "formatted_season": null, "formatted_added_date": "February 01, 2014"}, {"admitid": 254182, "institution": "Ucla", "programme": "Computer Science", "level": "PhD", "how": "E-mail", "decision": "Rejected", "date_of_notification": "2013-04-16", "date_of_record": "2013-04-16 09:27:11", "notes": "Rejection, rejections and more rejections. Got rejected even from my safety schools, can't believe have to wait 1 more year before I start grad school :(", "status": "I", "ip": "116.12.215.18", "uid": -1, "season": "F13", "ugpa": "0.00", "greq": 0, "grev": 0, "grew": "0.00", "gres": 0, "flag": 0, "user_id": 0, "deactivated_at": null, "formatted_notification_date": "16 Apr", "formatted_record_date": "April 2013", "formatted_season": null, "formatted_added_date": "April 16, 2013"}, {"admitid": 253648, "institution": "UCLA", "programme": "Computer Science", "level": "PhD", "how": "E-mail", "decision": "Accepted", "date_of_notification": "2013-04-13", "date_of_record": "2013-04-14 08:46:35", "notes": "He who laughs last, laughs longest. Hi California!", "status": "I", "ip": "74.125.185.23", "uid": 113836, "season": "F13", "ugpa": "0.00", "greq": 0, "grev": 0, "grew": "0.00", "gres": 0, "flag": 0, "user_id": 0, "deactivated_at": null, "formatted_notification_date": "13 Apr", "formatted_record_date": "April 2013", "formatted_season": null, "formatted_added_date": "April 14, 2013"}, {"admitid": 252496, "institution": "UCLA", "programme": "Computer Science", "level": "PhD", "how": "E-mail", "decision": "Rejected", "date_of_notification": "2013-04-10", "date_of_record": "2013-04-10 17:43:56", "notes": "", "status": "I", "ip": "125.33.178.75", "uid": -1, "season": "F13", "ugpa": "0.00", "greq": 0, "grev": 0, "grew": "0.00", "gres": 0, "flag": 0, "user_id": 0, "deactivated_at": null, "formatted_notification_date": "10 Apr", "formatted_record_date": "April 2013", "formatted_season": null, "formatted_added_date": "April 10, 2013"}, {"admitid": 251291, "institution": "UCLA", "programme": "Computer Science", "level": "PhD", "how": "E-mail", "decision": "Rejected", "date_of_notification": "2013-03-26", "date_of_record": "2013-04-06 08:23:46", "notes": "they said this year there were 840 applications for 70 seats for MS, so I had no option to be considered for MS", "status": "I", "ip": "79.165.204.33", "uid": -1, "season": "F13", "ugpa": "0.00", "greq": 0, "grev": 0, "grew": "0.00", "gres": 0, "flag": 0, "user_id": 0, "deactivated_at": null, "formatted_notification_date": "26 Mar", "formatted_record_date": "April 2013", "formatted_season": null, "formatted_added_date": "April 06, 2013"}, {"admitid": 246666, "institution": "UCLA", "programme": "Computer Science", "level": "PhD", "how": "E-mail", "decision": "Rejected", "date_of_notification": "2013-03-26", "date_of_record": "2013-03-26 19:27:15", "notes": "", "status": "I", "ip": "151.239.34.201", "uid": -1, "season": "F13", "ugpa": "0.00", "greq": 0, "grev": 0, "grew": "0.00", "gres": 0, "flag": 0, "user_id": 0, "deactivated_at": null, "formatted_notification_date": "26 Mar", "formatted_record_date": "March 2013", "formatted_season": null, "formatted_added_date": "March 26, 2013"}, {"admitid": 246415, "institution": "UCLA", "programme": "Computer Science", "level": "PhD", "how": "E-mail", "decision": "Rejected", "date_of_notification": "2013-03-26", "date_of_record": "2013-03-26 10:39:43", "notes": "Are doors closing ?", "status": "I", "ip": "111.240.113.127", "uid": -1, "season": "F13", "ugpa": "0.00", "greq": 0, "grev": 0, "grew": "0.00", "gres": 0, "flag": 0, "user_id": 0, "deactivated_at": null, "formatted_notification_date": "26 Mar", "formatted_record_date": "March 2013", "formatted_season": null, "formatted_added_date": "March 26, 2013"}, {"admitid": 238150, "institution": "UCLA", "programme": "Computer Science", "level": "PhD", "how": "E-mail", "decision": "Rejected", "date_of_notification": "2013-03-13", "date_of_record": "2013-03-13 22:32:45", "notes": "Applied for PHD. Admitted to MS without funding. Sigh:(", "status": "U", "ip": "129.93.5.133", "uid": -1, "season": "F13", "ugpa": "0.00", "greq": 0, "grev": 0, "grew": "0.00", "gres": 0, "flag": 0, "user_id": 0, "deactivated_at": null, "formatted_notification_date": "13 Mar", "formatted_record_date": "March 2013", "formatted_season": null, "formatted_added_date": "March 13, 2013"}, {"admitid": 231966, "institution": "UCLA", "programme": "Computer Science", "level": "PhD", "how": "E-mail", "decision": "Accepted", "date_of_notification": "2013-03-04", "date_of_record": "2013-03-07 10:36:42", "notes": "", "status": "I", "ip": "207.46.92.17", "uid": -1, "season": "F13", "ugpa": "3.68", "greq": 660, "grev": 800, "grew": "3.50", "gres": 0, "flag": 0, "user_id": 0, "deactivated_at": null, "formatted_notification_date": "4 Mar", "formatted_record_date": "March 2013", "formatted_season": null, "formatted_added_date": "March 07, 2013"}, {"admitid": 230023, "institution": "UCLA", "programme": "Computer Science", "level": "PhD", "how": "E-mail", "decision": "Accepted", "date_of_notification": "2013-03-05", "date_of_record": "2013-03-05 21:25:46", "notes": "I've been getting bizarre emails for the last two weeks, but no official notice until today. Two year fellowship!", "status": "A", "ip": "171.66.189.80", "uid": 0, "season": "F13", "ugpa": "0.00", "greq": 0, "grev": 0, "grew": "0.00", "gres": 0, "flag": 0, "user_id": 0, "deactivated_at": null, "formatted_notification_date": "5 Mar", "formatted_record_date": "March 2013", "formatted_season": null, "formatted_added_date": "March 05, 2013"}, {"admitid": 229973, "institution": "UCLA", "programme": "Computer Science", "level": "PhD", "how": "E-mail", "decision": "Accepted", "date_of_notification": "2013-03-05", "date_of_record": "2013-03-05 20:44:02", "notes": "finally got the official letter. So excited.", "status": "I", "ip": "76.73.3.220", "uid": -1, "season": "F13", "ugpa": "3.85", "greq": 166, "grev": 148, "grew": "3.00", "gres": 0, "flag": 0, "user_id": 0, "deactivated_at": null, "formatted_notification_date": "5 Mar", "formatted_record_date": "March 2013", "formatted_season": null, "formatted_added_date": "March 05, 2013"}, {"admitid": 229623, "institution": "UCLA", "programme": "Computer Science", "level": "PhD", "how": "E-mail", "decision": "Accepted", "date_of_notification": "2013-03-05", "date_of_record": "2013-03-05 16:45:17", "notes": "Dear no dooshvari, I am really interested to see your resume, I was wondering if you could introduce your name? From Iran", "status": "I", "ip": "91.99.55.131", "uid": -1, "season": "F13", "ugpa": "0.00", "greq": 0, "grev": 0, "grew": "0.00", "gres": 0, "flag": 0, "user_id": 0, "deactivated_at": null, "formatted_notification_date": "5 Mar", "formatted_record_date": "March 2013", "formatted_season": null, "formatted_added_date": "March 05, 2013"}, {"admitid": 229565, "institution": "UCLA", "programme": "Computer Science", "level": "PhD", "how": "E-mail", "decision": "Accepted", "date_of_notification": "2013-03-05", "date_of_record": "2013-03-05 16:11:20", "notes": "1 year fellow. no dooshvari.", "status": "", "ip": "188.121.125.142", "uid": -1, "season": "F13", "ugpa": "0.00", "greq": 0, "grev": 0, "grew": "0.00", "gres": 0, "flag": 0, "user_id": 0, "deactivated_at": null, "formatted_notification_date": "5 Mar", "formatted_record_date": "March 2013", "formatted_season": null, "formatted_added_date": "March 05, 2013"}, {"admitid": 224306, "institution": "UCLA (University Of California Los Angeles)", "programme": "Computer Science", "level": "PhD", "how": "E-mail", "decision": "Accepted", "date_of_notification": "2013-02-27", "date_of_record": "2013-02-28 06:08:52", "notes": "", "status": "A", "ip": "129.244.135.104", "uid": -1, "season": "F13", "ugpa": "0.00", "greq": 0, "grev": 0, "grew": "0.00", "gres": 0, "flag": 0, "user_id": 0, "deactivated_at": null, "formatted_notification_date": "27 Feb", "formatted_record_date": "February 2013", "formatted_season": null, "formatted_added_date": "February 28, 2013"}, {"admitid": 224123, "institution": "UCLA", "programme": "Computer Science", "level": "PhD", "how": "E-mail", "decision": "Accepted", "date_of_notification": "2013-02-27", "date_of_record": "2013-02-28 03:03:42", "notes": "AI, did some unrelated research as an UG", "status": "A", "ip": "24.180.26.46", "uid": -1, "season": "F13", "ugpa": "0.00", "greq": 170, "grev": 166, "grew": "4.00", "gres": 0, "flag": 0, "user_id": 0, "deactivated_at": null, "formatted_notification_date": "27 Feb", "formatted_record_date": "February 2013", "formatted_season": null, "formatted_added_date": "February 28, 2013"}, {"admitid": 223024, "institution": "UCLA", "programme": "Computer Science", "level": "PhD", "how": "E-mail", "decision": "Accepted", "date_of_notification": "2013-02-22", "date_of_record": "2013-02-27 05:07:48", "notes": "", "status": "I", "ip": "106.115.61.50", "uid": -1, "season": "F13", "ugpa": "0.00", "greq": 0, "grev": 0, "grew": "0.00", "gres": 0, "flag": 0, "user_id": 0, "deactivated_at": null, "formatted_notification_date": "22 Feb", "formatted_record_date": "February 2013", "formatted_season": null, "formatted_added_date": "February 27, 2013"}, {"admitid": 177614, "institution": "UCLA", "programme": "Computer Science", "level": "PhD", "how": "E-mail", "decision": "Rejected", "date_of_notification": "2012-03-08", "date_of_record": "2012-03-08 12:02:46", "notes": "Although I already withdrawn my application and got confirmation, they rejected me on Feb. 22 and today once again...", "status": "I", "ip": "60.191.2.238", "uid": -1, "season": "F12", "ugpa": "0.00", "greq": 0, "grev": 0, "grew": "0.00", "gres": 0, "flag": 0, "user_id": 0, "deactivated_at": null, "formatted_notification_date": "8 Mar", "formatted_record_date": "March 2012", "formatted_season": null, "formatted_added_date": "March 08, 2012"}, {"admitid": 177048, "institution": "UCLA", "programme": "Computer Science", "level": "PhD", "how": "E-mail", "decision": "Rejected", "date_of_notification": "2012-03-07", "date_of_record": "2012-03-07 21:18:44", "notes": "how many times you wonna reject me, that's enough, I got it! OK I will not come to your **** school!!", "status": "A", "ip": "169.235.25.216", "uid": -1, "season": "F12", "ugpa": "0.00", "greq": 0, "grev": 0, "grew": "0.00", "gres": 0, "flag": 0, "user_id": 0, "deactivated_at": null, "formatted_notification_date": "7 Mar", "formatted_record_date": "March 2012", "formatted_season": null, "formatted_added_date": "March 07, 2012"}, {"admitid": 176919, "institution": "UCLA", "programme": "Computer Science", "level": "PhD", "how": "E-mail", "decision": "Rejected", "date_of_notification": "2012-03-07", "date_of_record": "2012-03-07 19:58:45", "notes": "After rejecting me on Feb 22nd, they find it  not enough, and reject me again today. What a UCLA!", "status": "U", "ip": "98.111.156.145", "uid": -1, "season": "F12", "ugpa": "3.10", "greq": 800, "grev": 660, "grew": "3.00", "gres": 0, "flag": 0, "user_id": 0, "deactivated_at": null, "formatted_notification_date": "7 Mar", "formatted_record_date": "March 2012", "formatted_season": null, "formatted_added_date": "March 07, 2012"}, {"admitid": 176826, "institution": "UCLA", "programme": "Computer Science", "level": "PhD", "how": "E-mail", "decision": "Rejected", "date_of_notification": "2012-03-07", "date_of_record": "2012-03-07 18:42:58", "notes": "", "status": "A", "ip": "174.252.52.182", "uid": -1, "season": "F12", "ugpa": "0.00", "greq": 0, "grev": 0, "grew": "0.00", "gres": 0, "flag": 0, "user_id": 0, "deactivated_at": null, "formatted_notification_date": "7 Mar", "formatted_record_date": "March 2012", "formatted_season": null, "formatted_added_date": "March 07, 2012"}, {"admitid": 170861, "institution": "UCLA", "programme": "Computer Science", "level": "PhD", "how": "E-mail", "decision": "Accepted", "date_of_notification": "2012-02-29", "date_of_record": "2012-02-29 19:30:10", "notes": "", "status": "", "ip": "75.82.11.14", "uid": 75791, "season": "F12", "ugpa": "0.00", "greq": 0, "grev": 0, "grew": "0.00", "gres": 0, "flag": 0, "user_id": 0, "deactivated_at": null, "formatted_notification_date": "29 Feb", "formatted_record_date": "February 2012", "formatted_season": null, "formatted_added_date": "February 29, 2012"}, {"admitid": 165799, "institution": "UCLA", "programme": "Computer Science", "level": "PhD", "how": "Website", "decision": "Rejected", "date_of_notification": "2012-02-23", "date_of_record": "2012-02-23 03:19:20", "notes": "", "status": "U", "ip": "131.95.31.196", "uid": -1, "season": "F12", "ugpa": "0.00", "greq": 0, "grev": 0, "grew": "0.00", "gres": 0, "flag": 0, "user_id": 0, "deactivated_at": null, "formatted_notification_date": "23 Feb", "formatted_record_date": "February 2012", "formatted_season": null, "formatted_added_date": "February 23, 2012"}, {"admitid": 165441, "institution": "UCLA", "programme": "Computer Science", "level": "PhD", "how": "E-mail", "decision": "Other", "date_of_notification": "2012-02-22", "date_of_record": "2012-02-22 20:30:52", "notes": "Indeed, they sent an email informing that the notifications this morning were sent by mistake. So, I guess all \"rejects\" posted here today were wrong....:D", "status": "I", "ip": "94.71.4.231", "uid": -1, "season": "F12", "ugpa": "0.00", "greq": 0, "grev": 0, "grew": "0.00", "gres": 0, "flag": 0, "user_id": 0, "deactivated_at": null, "formatted_notification_date": "22 Feb", "formatted_record_date": "February 2012", "formatted_season": null, "formatted_added_date": "February 22, 2012"}, {"admitid": 164987, "institution": "UCLA", "programme": "Computer Science", "level": "PhD", "how": "E-mail", "decision": "Rejected", "date_of_notification": "2012-02-22", "date_of_record": "2012-02-22 11:55:00", "notes": "Frustrated..", "status": "I", "ip": "166.111.138.24", "uid": -1, "season": "F12", "ugpa": "0.00", "greq": 0, "grev": 0, "grew": "0.00", "gres": 0, "flag": 0, "user_id": 0, "deactivated_at": null, "formatted_notification_date": "22 Feb", "formatted_record_date": "February 2012", "formatted_season": null, "formatted_added_date": "February 22, 2012"}, {"admitid": 164980, "institution": "UCLA", "programme": "Computer Science", "level": "PhD", "how": "E-mail", "decision": "Rejected", "date_of_notification": "2012-02-22", "date_of_record": "2012-02-22 11:34:05", "notes": "Admission expected, rejection received.", "status": "I", "ip": "205.185.125.191", "uid": -1, "season": "F12", "ugpa": "0.00", "greq": 0, "grev": 0, "grew": "0.00", "gres": 0, "flag": 0, "user_id": 0, "deactivated_at": null, "formatted_notification_date": "22 Feb", "formatted_record_date": "February 2012", "formatted_season": null, "formatted_added_date": "February 22, 2012"}, {"admitid": 164978, "institution": "UCLA", "programme": "Computer Science", "level": "PhD", "how": "E-mail", "decision": "Rejected", "date_of_notification": "2012-02-22", "date_of_record": "2012-02-22 11:23:05", "notes": "Yet another theory applicant. To all theory applicants, don't be discouraged by rejections because this field is the most competitive among all fields. Hope everyone can finally get a good place to go.", "status": "I", "ip": "1.162.89.24", "uid": -1, "season": "F12", "ugpa": "0.00", "greq": 0, "grev": 0, "grew": "0.00", "gres": 0, "flag": 0, "user_id": 0, "deactivated_at": null, "formatted_notification_date": "22 Feb", "formatted_record_date": "February 2012", "formatted_season": null, "formatted_added_date": "February 22, 2012"}, {"admitid": 164974, "institution": "UCLA", "programme": "Computer Science", "level": "PhD", "how": "E-mail", "decision": "Rejected", "date_of_notification": "2012-02-22", "date_of_record": "2012-02-22 10:59:35", "notes": "Theory applicant", "status": "I", "ip": "94.71.15.192", "uid": -1, "season": "F12", "ugpa": "0.00", "greq": 0, "grev": 0, "grew": "0.00", "gres": 0, "flag": 0, "user_id": 0, "deactivated_at": null, "formatted_notification_date": "22 Feb", "formatted_record_date": "February 2012", "formatted_season": null, "formatted_added_date": "February 22, 2012"}, {"admitid": 161254, "institution": "UCLA", "programme": "Computer Science", "level": "PhD", "how": "E-mail", "decision": "Rejected", "date_of_notification": "2012-02-16", "date_of_record": "2012-02-16 15:18:30", "notes": "", "status": "U", "ip": "65.14.229.26", "uid": -1, "season": "F12", "ugpa": "0.00", "greq": 0, "grev": 0, "grew": "0.00", "gres": 0, "flag": 0, "user_id": 0, "deactivated_at": null, "formatted_notification_date": "16 Feb", "formatted_record_date": "February 2012", "formatted_season": null, "formatted_added_date": "February 16, 2012"}, {"admitid": 160641, "institution": "UCLA", "programme": "Computer Science", "level": "PhD", "how": "E-mail", "decision": "Rejected", "date_of_notification": "2012-02-15", "date_of_record": "2012-02-15 19:30:22", "notes": "I thought I had a good application. Fuck UCLA; they have a lie in their website saying that admission rate is 151/431.", "status": "", "ip": "174.28.146.102", "uid": 40196, "season": "F12", "ugpa": "0.00", "greq": 0, "grev": 0, "grew": "0.00", "gres": 0, "flag": 0, "user_id": 0, "deactivated_at": null, "formatted_notification_date": "15 Feb", "formatted_record_date": "February 2012", "formatted_season": null, "formatted_added_date": "February 15, 2012"}, {"admitid": 160637, "institution": "UCLA", "programme": "Computer Science", "level": "PhD", "how": "E-mail", "decision": "Rejected", "date_of_notification": "2012-02-15", "date_of_record": "2012-02-15 19:22:14", "notes": "Really why????", "status": "I", "ip": "2.178.61.170", "uid": -1, "season": "F12", "ugpa": "0.00", "greq": 0, "grev": 0, "grew": "0.00", "gres": 0, "flag": 0, "user_id": 0, "deactivated_at": null, "formatted_notification_date": "15 Feb", "formatted_record_date": "February 2012", "formatted_season": null, "formatted_added_date": "February 15, 2012"}, {"admitid": 160531, "institution": "UCLA", "programme": "Computer Science", "level": "PhD", "how": "E-mail", "decision": "Rejected", "date_of_notification": "2012-02-15", "date_of_record": "2012-02-15 17:21:49", "notes": "First result, definitely sad!", "status": "I", "ip": "94.182.76.239", "uid": -1, "season": "F12", "ugpa": "0.00", "greq": 0, "grev": 0, "grew": "0.00", "gres": 0, "flag": 0, "user_id": 0, "deactivated_at": null, "formatted_notification_date": "15 Feb", "formatted_record_date": "February 2012", "formatted_season": null, "formatted_added_date": "February 15, 2012"}, {"admitid": 160378, "institution": "UCLA", "programme": "Computer Science", "level": "PhD", "how": "E-mail", "decision": "Rejected", "date_of_notification": "2012-02-15", "date_of_record": "2012-02-15 13:45:06", "notes": "", "status": "U", "ip": "174.62.174.107", "uid": -1, "season": "F12", "ugpa": "0.00", "greq": 0, "grev": 0, "grew": "0.00", "gres": 0, "flag": 0, "user_id": 0, "deactivated_at": null, "formatted_notification_date": "15 Feb", "formatted_record_date": "February 2012", "formatted_season": null, "formatted_added_date": "February 15, 2012"}, {"admitid": 160377, "institution": "UCLA", "programme": "Computer Science", "level": "PhD", "how": "E-mail", "decision": "Rejected", "date_of_notification": "2012-02-15", "date_of_record": "2012-02-15 13:44:31", "notes": "", "status": "I", "ip": "2.178.61.170", "uid": -1, "season": "F12", "ugpa": "0.00", "greq": 0, "grev": 0, "grew": "0.00", "gres": 0, "flag": 0, "user_id": 0, "deactivated_at": null, "formatted_notification_date": "15 Feb", "formatted_record_date": "February 2012", "formatted_season": null, "formatted_added_date": "February 15, 2012"}, {"admitid": 160338, "institution": "UCLA", "programme": "Computer Science", "level": "PhD", "how": "E-mail", "decision": "Rejected", "date_of_notification": "2012-02-15", "date_of_record": "2012-02-15 11:52:18", "notes": "First reject. very sad =(", "status": "", "ip": "212.175.32.136", "uid": -1, "season": "F12", "ugpa": "0.00", "greq": 0, "grev": 0, "grew": "0.00", "gres": 0, "flag": 0, "user_id": 0, "deactivated_at": null, "formatted_notification_date": "15 Feb", "formatted_record_date": "February 2012", "formatted_season": null, "formatted_added_date": "February 15, 2012"}, {"admitid": 160332, "institution": "UCLA", "programme": "Computer Science", "level": "PhD", "how": "E-mail", "decision": "Rejected", "date_of_notification": "2012-02-15", "date_of_record": "2012-02-15 11:40:39", "notes": "", "status": "I", "ip": "213.233.169.205", "uid": -1, "season": "F12", "ugpa": "0.00", "greq": 0, "grev": 0, "grew": "0.00", "gres": 0, "flag": 0, "user_id": 0, "deactivated_at": null, "formatted_notification_date": "15 Feb", "formatted_record_date": "February 2012", "formatted_season": null, "formatted_added_date": "February 15, 2012"}, {"admitid": 160325, "institution": "Ucla", "programme": "Computer Science", "level": "PhD", "how": "E-mail", "decision": "Rejected", "date_of_notification": "2012-02-14", "date_of_record": "2012-02-15 11:18:00", "notes": "", "status": "I", "ip": "213.233.170.141", "uid": -1, "season": "F12", "ugpa": "0.00", "greq": 160, "grev": 147, "grew": "3.50", "gres": 0, "flag": 0, "user_id": 0, "deactivated_at": null, "formatted_notification_date": "14 Feb", "formatted_record_date": "February 2012", "formatted_season": null, "formatted_added_date": "February 15, 2012"}, {"admitid": 160324, "institution": "UCLA", "programme": "Computer Science", "level": "PhD", "how": "E-mail", "decision": "Rejected", "date_of_notification": "2012-02-15", "date_of_record": "2012-02-15 11:17:31", "notes": "", "status": "I", "ip": "120.204.232.42", "uid": -1, "season": "F12", "ugpa": "0.00", "greq": 0, "grev": 0, "grew": "0.00", "gres": 0, "flag": 0, "user_id": 0, "deactivated_at": null, "formatted_notification_date": "15 Feb", "formatted_record_date": "February 2012", "formatted_season": null, "formatted_added_date": "February 15, 2012"}, {"admitid": 127978, "institution": "UCLA Henry Samuel College Of Engineering", "programme": "Computer Science (CS)", "level": "PhD", "how": "E-mail", "decision": "Rejected", "date_of_notification": "2011-03-08", "date_of_record": "2011-03-08 11:01:33", "notes": "E-mail telling me to consult the web-page. :(", "status": "I", "ip": "195.235.92.26", "uid": -1, "season": "F11", "ugpa": "0.00", "greq": 790, "grev": 620, "grew": "4.00", "gres": 0, "flag": 0, "user_id": 0, "deactivated_at": null, "formatted_notification_date": "8 Mar", "formatted_record_date": "March 2011", "formatted_season": null, "formatted_added_date": "March 08, 2011"}, {"admitid": 111710, "institution": "UCLA, Toronto", "programme": "Computer Science", "level": "PhD", "how": "Other", "decision": "Other", "date_of_notification": "2011-02-12", "date_of_record": "2011-02-12 16:10:33", "notes": "P.S. Accepted by both", "status": "", "ip": "79.131.172.177", "uid": -1, "season": "F11", "ugpa": "0.00", "greq": 0, "grev": 0, "grew": "0.00", "gres": 0, "flag": 0, "user_id": 0, "deactivated_at": null, "formatted_notification_date": "12 Feb", "formatted_record_date": "February 2011", "formatted_season": null, "formatted_added_date": "February 12, 2011"}]